{
    "name": "discord-reader",
    "category": "community",
    "source_url": "https://github.com/himself65/finance-skills",
    "supported_models": [
        "All"
    ],
    "capabilities": [],
    "install_runtime": "npx",
    "description": "Read Discord for financial research using opencli (read-only). Use this skill whenever the user wants to read Discord channels, search for messages in trading servers, view guild/channel info, monitor crypto or market discussion groups, or gather financial sentiment from Discord. Triggers include: \"check my Discord\", \"search Discord for\", \"read Discord messages\", \"what's happening in the trading Discord\", \"show Discord channels\", \"list my servers\", \"Discord sentiment on BTC\", \"what are people saying in Discord about AAPL\", \"monitor crypto Discord\", any mention of Discord in context of reading financial news, market research, or trading community discussions. This skill is READ-ONLY \u2014 it does NOT support sending messages, reacting, or any write operations."
}